W4/BCD_Up_Counter.v
module BCD_Up_Counter(clk, rst_asyn, Q_out);
input clk; //輸入clock
input rst_asyn; //輸入rst
output [3:0] Q_out; //輸出
reg [3:0] Q_out;

    always@ (posedge clk or posedge rst_asyn)
        begin
            if (rst_asyn)           //如果rst==1清除
                Q_out=0;
            else if (Q_out == 9)    //如果Q_out累加到九清除
                Q_out=0;
            else
                Q_out=Q_out+1;    
        end
endmodule

W4/BCD_Up_Counter_tb.v
module BCD_Counter_tb;
reg clk,rst_asyn;    //輸入
wire [3:0] Q_out;   //輸出

initial begin
    #0;             //0秒時執行forever
    forever         //類是無限迴圈(#是並行處理)
    begin
        clk = 1'b0;
        #10 clk = 1'b1;
        #10;
    end
end

initial begin
    #0 rst_asyn=1'b1;   //rst
    #10 rst_asyn=1'b0;
    #27 rst_asyn=1'b1;  //按下rst
    #1 rst_asyn=1'b0;
    #400 $finish;
end


BCD_Up_Counter BCD_Up_Counter_tb(.clk(clk), .rst_asyn(rst_asyn), .Q_out(Q_out));
initial begin
    $dumpfile("BCD_Up_Counter.vcd");
    $dumpvars(0, BCD_Up_Counter_tb);
end
endmodule

W4/BCD_Up_Counter.vcd
$date
	Sun May 01 23:10:49 2022
$end
$version
	Icarus Verilog
$end
$timescale
	1s
$end
$scope module BCD_Counter_tb $end
$scope module BCD_Up_Counter_tb $end
$var wire 1 ! clk $end
$var wire 1 " rst_asyn $end
$var reg 4 # Q_out [3:0] $end
$upscope $end
$upscope $end
$enddefinitions $end
#0
$dumpvars
b0 #
1"
0!
$end
#10
b1 #
0"
1!
#20
0!
#30
b10 #
1!
#37
b0 #
1"
#38
0"
#40
0!
#50
b1 #
1!
#60
0!
#70
b10 #
1!
#80
0!
#90
b11 #
1!
#100
0!
#110
b100 #
1!
#120
0!
#130
b101 #
1!
#140
0!
#150
b110 #
1!
#160
0!
#170
b111 #
1!
#180
0!
#190
b1000 #
1!
#200
0!
#210
b1001 #
1!
#220
0!
#230
b0 #
1!
#240
0!
#250
b1 #
1!
#260
0!
#270
b10 #
1!
#280
0!
#290
b11 #
1!
#300
0!
#310
b100 #
1!
#320
0!
#330
b101 #
1!
#340
0!
#350
b110 #
1!
#360
0!
#370
b111 #
1!
#380
0!
#390
b1000 #
1!
#400
0!
#410
b1001 #
1!
#420
0!
#430
b0 #
1!
